sim/uart_input_handler.v
module uart_input_handler(
    clk,
    rst,
    byte_available,
    byte,
    command,
	address,
    data,
    ready,
);

//incomming signals
input clk;
input rst;
input byte_available;
input [7:0]byte;

//outgoing control
output reg [31:0] command;
output reg [31:0] address;
output reg [31:0] data;
output reg ready;

//STATES
parameter STATE_IDLE             = 8'h0;
parameter STATE_READ_ID  		 = 8'h1;
parameter STATE_READ_CONTROL     = 8'h2;
parameter STATE_READ_ADDRESS   	 = 8'h3;
parameter STATE_READ_DATA        = 8'h4;

parameter CHAR_L 				= 8'h4C;

parameter CHAR_0 				= 8'h30;
parameter CHAR_HEX_OFFSET 		= 8'h37;
parameter CHAR_A				= 8'h41;
parameter CHAR_F				= 8'h46;

//Registers
reg [7:0]  r_STATE    		= 'b0;

//reg r_low_byte          	= 0;
reg [3:0] r_nibble_count	= 4'h0;
reg [15:0] r_count      	= 0;

reg r_prev_byte_available = 0;


//Wire
wire pos_edge_byte_available;

//Assign
assign pos_edge_byte_available = (byte_available & ~r_prev_byte_available);

//Synchronous
always @ (posedge clk) begin
    r_prev_byte_available <= byte_available;
end

always @ (posedge clk) begin

    if (rst) begin
        command     	<= 32'h0000;
		address			<= 32'h0000;
		data			<= 32'h0000;
        r_STATE     	<= STATE_IDLE;
		r_nibble_count	<= 4'h0;
        //r_low_byte  <= 0;
		ready		<= 0;

    end
    else begin
        //main state machine goes here
        case (r_STATE)
            STATE_IDLE: begin
				command			<= 32'h0000;
				address			<= 32'h0000;
				data			<= 32'h0000;
				r_nibble_count	<= 4'h0;
				ready			<= 0;
                if (pos_edge_byte_available) begin
                    r_STATE     <= STATE_READ_ID;
                end
            end
            STATE_READ_ID: begin
                if (byte == CHAR_L) begin
                    //read the first of byte
                    r_STATE     	<= STATE_READ_CONTROL;
					r_nibble_count	<= 4'h0;
                end
                else begin
                    r_STATE 		<= STATE_IDLE;
                end
			end
            STATE_READ_CONTROL: begin
                
                if (pos_edge_byte_available) begin
                    if ((byte < CHAR_0) || 
						((byte > CHAR_0 + 10) && (byte < CHAR_A)) || 
						(byte > CHAR_F)) begin
						/*
						something went wront reset... this code could be put
						outside all of the states, but within the state its
						easier to understand the code
						*/
                        r_STATE    <=    STATE_READ_ID;
                    end
                    else begin
					/*
						read a byte, increment the count and put data into the
						command register MSB first
						*/
						if (byte >= CHAR_A && byte <= CHAR_F) begin
							//A - F value
							command 		<= (command[31:0] << 4) + (byte - CHAR_HEX_OFFSET);
						end
						else begin
							//0-9 value
							command 		<= (command[31:0] << 4) + (byte - CHAR_0);
						end
						r_nibble_count 	<= r_nibble_count + 1;	

						if (r_nibble_count >= 7) begin
							r_STATE			<= STATE_READ_ADDRESS;
							r_nibble_count 	<= 4'h0;
						end
	
                    end
                end
            end
            STATE_READ_ADDRESS: begin
                //read the size
                if (pos_edge_byte_available) begin
                    if ((byte < CHAR_0) || 
						((byte > CHAR_0 + 10) && (byte < CHAR_A)) || 
						(byte > CHAR_F)) begin
						/*
						something went wront reset... this code could be put
						outside all of the states, but within the state its
						easier to understand the code
						*/
                        r_STATE    <=    STATE_READ_ID;
                    end
                    else begin
						if (byte >= CHAR_A && byte <= CHAR_F) begin
							//A - F value
							address 		<= (address[31:0] << 4) + (byte - CHAR_HEX_OFFSET);
						end
						else begin
							//0-9 value
							address 		<= (address[31:0] << 4) + (byte - CHAR_0);
						end
				
						r_nibble_count 	<= r_nibble_count + 1;
					
						if (r_nibble_count >= 7) begin
							r_STATE			<= STATE_READ_DATA;
							r_nibble_count 	<= 4'h0;
						end
                    end                
                end
            end
            STATE_READ_DATA : begin
                if (pos_edge_byte_available) begin
					if ((byte < CHAR_0) || 
						((byte > CHAR_0 + 10) && (byte < CHAR_A)) || 
						(byte > CHAR_F)) begin
						/*
						something went wront reset... this code could be put
						outside all of the states, but within the state its
						easier to understand the code
						*/
                        r_STATE    <=    STATE_READ_ID;
                    end
                    else begin
						if (byte >= CHAR_A && byte <= CHAR_F) begin
							//A - F value
							data 		<= (data[31:0] << 4) + (byte - CHAR_HEX_OFFSET);
						end
						else begin
							//0-9 value
							data 		<= (data[31:0] << 4) + (byte - CHAR_0);
						end

						r_nibble_count	<= r_nibble_count + 1;

						if (r_nibble_count >= 7) begin
							r_STATE			<= STATE_IDLE;
							r_nibble_count	<= 4'h0;
						end
                    end
                end
            end
            default: begin
                command         <= 8'h0;
                r_STATE         <= STATE_IDLE;
            end
        endcase
        
    end
end
endmodule

sim/uart_input_handler_tb.v
module uart_input_handler_tb;
	//make a reset that pulses once
	reg rst = 0;
	reg clk = 0;

	//input handler specific registers
	reg 			byte_available 	= 0;
	reg  [7:0] 		byte			= 0;
	wire [31:0]		command;
	wire [31:0]		address_in;
	wire [31:0] 	data_in;
	wire 			ready;

	uart_input_handler ih (
		.clk(clk),
		.rst(rst),
		.byte_available(byte_available),
		.byte(byte),
		.command(command),
		.address(address_in),
		.data(data_in),
		.ready(ready));

	initial begin
		$dumpfile("design.vcd");
		$dumpvars(0, uart_input_handler_tb);
		$dumpvars(0, ih);

		#5
					rst = 1;
		#5 		
					rst = 0;
		#5		
//SEND ID as ASCII 'L'
					byte = 16'h4C;
					byte_available = 1;
		#5		
					byte_available = 0;

//Send command "10000009"

//Send command '0' as ASCII '0'
		#5
					byte = 16'h31;
					byte_available = 1;
		#5
					byte_available = 0;

		#5
					byte = 16'h30;
					byte_available = 1;
		#5
					byte_available = 0;

		#5
					byte = 16'h30;
					byte_available = 1;
		#5
					byte_available = 0;

		#5
					byte = 16'h30;
					byte_available = 1;
		#5
					byte_available = 0;
		
		#5		
					byte = 16'h30;
					byte_available = 1;
		#5		
					byte_available = 0;

		#5
					byte = 16'h30;
					byte_available = 1;
		#5	
					byte_available = 0;

		#5
					byte = 16'h30;
					byte_available = 1;
		#5	
					byte_available = 0;

		#5
					byte = 16'h39;
					byte_available = 1;
		#5	
					byte_available = 0;

//Send data 0x0123456789ABCDEF
		#5	
					byte = 16'h30;
					byte_available = 1;
		#5		
					byte_available = 0;
		#5	
					byte = 16'h31;
					byte_available = 1;
		#5		
					byte_available = 0;
		#5	
					byte = 16'h32;
					byte_available = 1;
		#5		
					byte_available = 0;
		#5	
					byte = 16'h33;
					byte_available = 1;
		#5		
					byte_available = 0;
		#5	
					byte = 16'h34;
					byte_available = 1;
		#5		
					byte_available = 0;
		#5	
					byte = 16'h35;
					byte_available = 1;
		#5		
					byte_available = 0;
		#5
					byte = 16'h36;
					byte_available = 1;
		#5		
					byte_available = 0;
		#5	
					byte = 16'h37;
					byte_available = 1;
		#5		
					byte_available = 0;
		#5
					byte = 16'h38;
					byte_available = 1;
		#5		
					byte_available = 0;
		#5		

					byte = 16'h39;
					byte_available = 1;
		#5		
					byte_available = 0;
		#5		
	
					byte = 16'h41;
					byte_available = 1;
		#5		
					byte_available = 0;
		#5		

					byte = 16'h42;
					byte_available = 1;
		#5		
					byte_available = 0;
		#5		
	
					byte = 16'h43;
					byte_available = 1;
		#5		
					byte_available = 0;
		#5		

					byte = 16'h44;
					byte_available = 1;
		#5		
					byte_available = 0;
		#5		

					byte = 16'h45;
					byte_available = 1;
		#5		
					byte_available = 0;
		#5		

					byte = 16'h46;
					byte_available = 1;
		#5		
					byte_available = 0;
		#5		
	

//finished
		#5		
					byte = 16'h30;
					byte_available = 1;
		#5
					byte_available = 0;

		#5 	
					$finish;

	end

	always #1 clk = ~clk;

	initial $monitor ("%t: byte:%h, control:%H, address:%H, ready:%H, data in:%H", $time, byte, command, address_in, ready, data_in);
endmodule

sim/design.vcd
$date
	Wed Jun 29 17:54:01 2011
$end
$version
	Icarus Verilog
$end
$timescale
	1s
$end
$scope module uart_input_handler_tb $end
$var wire 32 ! address_in [31:0] $end
$var wire 32 " command [31:0] $end
$var wire 32 # data_in [31:0] $end
$var wire 1 $ ready $end
$var reg 8 % byte [7:0] $end
$var reg 1 & byte_available $end
$var reg 1 ' clk $end
$var reg 1 ( rst $end
$scope module ih $end
$var wire 8 ) byte [7:0] $end
$var wire 1 * byte_available $end
$var wire 1 + clk $end
$var wire 1 , pos_edge_byte_available $end
$var wire 1 - rst $end
$var reg 32 . address [31:0] $end
$var reg 32 / command [31:0] $end
$var reg 32 0 data [31:0] $end
$var reg 8 1 r_STATE [7:0] $end
$var reg 16 2 r_count [15:0] $end
$var reg 4 3 r_nibble_count [3:0] $end
$var reg 1 4 r_prev_byte_available $end
$var reg 1 5 ready $end
$upscope $end
$upscope $end
$scope module uart_input_handler_tb $end
$scope module ih $end
$upscope $end
$upscope $end
$enddefinitions $end
#0
$dumpvars
x5
04
b0 3
b0 2
b0 1
bx 0
bx /
bx .
0-
0,
0+
0*
b0 )
0(
0'
0&
b0 %
x$
bx #
bx "
bx !
$end
#1
05
0$
b0 0
b0 #
b0 .
b0 !
b0 /
b0 "
1'
1+
#2
0'
0+
#3
1'
1+
#4
0'
0+
#5
1'
1+
1(
1-
#6
0'
0+
#7
1'
1+
#8
0'
0+
#9
1'
1+
#10
0'
0+
0(
0-
#11
1'
1+
#12
0'
0+
#13
1'
1+
#14
0'
0+
#15
b1 1
14
0,
1'
1+
1&
1*
b1001100 %
b1001100 )
#16
0'
0+
#17
b10 1
1'
1+
#18
0'
0+
#19
1'
1+
#20
0'
0+
0&
0*
#21
04
1'
1+
#22
0'
0+
#23
1'
1+
#24
0'
0+
#25
14
b1 3
b1 /
b1 "
0,
1'
1+
1&
1*
b110001 %
b110001 )
#26
0'
0+
#27
1'
1+
#28
0'
0+
#29
1'
1+
#30
0'
0+
0&
0*
#31
04
1'
1+
#32
0'
0+
#33
1'
1+
#34
0'
0+
#35
b10 3
b10000 /
b10000 "
14
0,
1'
1+
1&
1*
b110000 %
b110000 )
#36
0'
0+
#37
1'
1+
#38
0'
0+
#39
1'
1+
#40
0'
0+
0&
0*
#41
04
1'
1+
#42
0'
0+
#43
1'
1+
#44
0'
0+
#45
14
b11 3
b100000000 /
b100000000 "
0,
1'
1+
1&
1*
#46
0'
0+
#47
1'
1+
#48
0'
0+
#49
1'
1+
#50
0'
0+
0&
0*
#51
04
1'
1+
#52
0'
0+
#53
1'
1+
#54
0'
0+
#55
b100 3
b1000000000000 /
b1000000000000 "
14
0,
1'
1+
1&
1*
#56
0'
0+
#57
1'
1+
#58
0'
0+
#59
1'
1+
#60
0'
0+
0&
0*
#61
04
1'
1+
#62
0'
0+
#63
1'
1+
#64
0'
0+
#65
14
b101 3
b10000000000000000 /
b10000000000000000 "
0,
1'
1+
1&
1*
#66
0'
0+
#67
1'
1+
#68
0'
0+
#69
1'
1+
#70
0'
0+
0&
0*
#71
04
1'
1+
#72
0'
0+
#73
1'
1+
#74
0'
0+
#75
b110 3
b100000000000000000000 /
b100000000000000000000 "
14
0,
1'
1+
1&
1*
#76
0'
0+
#77
1'
1+
#78
0'
0+
#79
1'
1+
#80
0'
0+
0&
0*
#81
04
1'
1+
#82
0'
0+
#83
1'
1+
#84
0'
0+
#85
14
b111 3
b1000000000000000000000000 /
b1000000000000000000000000 "
0,
1'
1+
1&
1*
#86
0'
0+
#87
1'
1+
#88
0'
0+
#89
1'
1+
#90
0'
0+
0&
0*
#91
04
1'
1+
#92
0'
0+
#93
1'
1+
#94
0'
0+
#95
b11 1
b0 3
b10000000000000000000000001001 /
b10000000000000000000000001001 "
14
0,
1'
1+
1&
1*
b111001 %
b111001 )
#96
0'
0+
#97
1'
1+
#98
0'
0+
#99
1'
1+
#100
0'
0+
0&
0*
#101
04
1'
1+
#102
0'
0+
#103
1'
1+
#104
0'
0+
#105
14
b1 3
0,
1'
1+
1&
1*
b110000 %
b110000 )
#106
0'
0+
#107
1'
1+
#108
0'
0+
#109
1'
1+
#110
0'
0+
0&
0*
#111
04
1'
1+
#112
0'
0+
#113
1'
1+
#114
0'
0+
#115
b10 3
b1 .
b1 !
14
0,
1'
1+
1&
1*
b110001 %
b110001 )
#116
0'
0+
#117
1'
1+
#118
0'
0+
#119
1'
1+
#120
0'
0+
0&
0*
#121
04
1'
1+
#122
0'
0+
#123
1'
1+
#124
0'
0+
#125
14
b11 3
b10010 .
b10010 !
0,
1'
1+
1&
1*
b110010 %
b110010 )
#126
0'
0+
#127
1'
1+
#128
0'
0+
#129
1'
1+
#130
0'
0+
0&
0*
#131
04
1'
1+
#132
0'
0+
#133
1'
1+
#134
0'
0+
#135
b100 3
b100100011 .
b100100011 !
14
0,
1'
1+
1&
1*
b110011 %
b110011 )
#136
0'
0+
#137
1'
1+
#138
0'
0+
#139
1'
1+
#140
0'
0+
0&
0*
#141
04
1'
1+
#142
0'
0+
#143
1'
1+
#144
0'
0+
#145
14
b101 3
b1001000110100 .
b1001000110100 !
0,
1'
1+
1&
1*
b110100 %
b110100 )
#146
0'
0+
#147
1'
1+
#148
0'
0+
#149
1'
1+
#150
0'
0+
0&
0*
#151
04
1'
1+
#152
0'
0+
#153
1'
1+
#154
0'
0+
#155
b110 3
b10010001101000101 .
b10010001101000101 !
14
0,
1'
1+
1&
1*
b110101 %
b110101 )
#156
0'
0+
#157
1'
1+
#158
0'
0+
#159
1'
1+
#160
0'
0+
0&
0*
#161
04
1'
1+
#162
0'
0+
#163
1'
1+
#164
0'
0+
#165
14
b111 3
b100100011010001010110 .
b100100011010001010110 !
0,
1'
1+
1&
1*
b110110 %
b110110 )
#166
0'
0+
#167
1'
1+
#168
0'
0+
#169
1'
1+
#170
0'
0+
0&
0*
#171
04
1'
1+
#172
0'
0+
#173
1'
1+
#174
0'
0+
#175
b100 1
b0 3
b1001000110100010101100111 .
b1001000110100010101100111 !
14
0,
1'
1+
1&
1*
b110111 %
b110111 )
#176
0'
0+
#177
1'
1+
#178
0'
0+
#179
1'
1+
#180
0'
0+
0&
0*
#181
04
1'
1+
#182
0'
0+
#183
1'
1+
#184
0'
0+
#185
14
b1 3
b1000 0
b1000 #
0,
1'
1+
1&
1*
b111000 %
b111000 )
#186
0'
0+
#187
1'
1+
#188
0'
0+
#189
1'
1+
#190
0'
0+
0&
0*
#191
04
1'
1+
#192
0'
0+
#193
1'
1+
#194
0'
0+
#195
b10 3
b10001001 0
b10001001 #
14
0,
1'
1+
1&
1*
b111001 %
b111001 )
#196
0'
0+
#197
1'
1+
#198
0'
0+
#199
1'
1+
#200
0'
0+
0&
0*
#201
04
1'
1+
#202
0'
0+
#203
1'
1+
#204
0'
0+
#205
14
b11 3
b100010011010 0
b100010011010 #
0,
1'
1+
1&
1*
b1000001 %
b1000001 )
#206
0'
0+
#207
1'
1+
#208
0'
0+
#209
1'
1+
#210
0'
0+
0&
0*
#211
04
1'
1+
#212
0'
0+
#213
1'
1+
#214
0'
0+
#215
b100 3
b1000100110101011 0
b1000100110101011 #
14
0,
1'
1+
1&
1*
b1000010 %
b1000010 )
#216
0'
0+
#217
1'
1+
#218
0'
0+
#219
1'
1+
#220
0'
0+
0&
0*
#221
04
1'
1+
#222
0'
0+
#223
1'
1+
#224
0'
0+
#225
14
b101 3
b10001001101010111100 0
b10001001101010111100 #
0,
1'
1+
1&
1*
b1000011 %
b1000011 )
#226
0'
0+
#227
1'
1+
#228
0'
0+
#229
1'
1+
#230
0'
0+
0&
0*
#231
04
1'
1+
#232
0'
0+
#233
1'
1+
#234
0'
0+
#235
b110 3
b100010011010101111001101 0
b100010011010101111001101 #
14
0,
1'
1+
1&
1*
b1000100 %
b1000100 )
#236
0'
0+
#237
1'
1+
#238
0'
0+
#239
1'
1+
#240
0'
0+
0&
0*
#241
04
1'
1+
#242
0'
0+
#243
1'
1+
#244
0'
0+
#245
14
b111 3
b1000100110101011110011011110 0
b1000100110101011110011011110 #
0,
1'
1+
1&
1*
b1000101 %
b1000101 )
#246
0'
0+
#247
1'
1+
#248
0'
0+
#249
1'
1+
#250
0'
0+
0&
0*
#251
04
1'
1+
#252
0'
0+
#253
1'
1+
#254
0'
0+
#255
b0 1
b0 3
b10001001101010111100110111101111 0
b10001001101010111100110111101111 #
14
0,
1'
1+
1&
1*
b1000110 %
b1000110 )
#256
0'
0+
#257
b0 0
b0 #
b0 .
b0 !
b0 /
b0 "
1'
1+
#258
0'
0+
#259
1'
1+
#260
0'
0+
0&
0*
#261
04
1'
1+
#262
0'
0+
#263
1'
1+
#264
0'
0+
#265
1'
1+
#266
0'
0+
#267
1'
1+
#268
0'
0+
#269
1'
1+
#270
1,
0'
0+
1&
1*
b110000 %
b110000 )
#271
0,
b1 1
14
1'
1+
#272
0'
0+
#273
b0 1
1'
1+
#274
0'
0+
#275
04
1'
1+
0&
0*
